README.md
setup.py
automaxprocs/__init__.py
automaxprocs/maxprocs.py
automaxprocs/version.py
automaxprocs/cgroups/__init__.py
automaxprocs/cgroups/cgroup.py
automaxprocs/cgroups/cgroups.py
automaxprocs/cgroups/errors.py
automaxprocs/cgroups/mountpoint.py
automaxprocs/cgroups/subsys.py
automaxprocs/runtime/__init__.py
automaxprocs/runtime/cpu_quota_linux.py
automaxprocs/runtime/cpu_quota_unsupported.py
automaxprocs/runtime/runtime.py
pyautomaxprocs.egg-info/PKG-INFO
pyautomaxprocs.egg-info/SOURCES.txt
pyautomaxprocs.egg-info/dependency_links.txt
pyautomaxprocs.egg-info/not-zip-safe
pyautomaxprocs.egg-info/requires.txt
pyautomaxprocs.egg-info/top_level.txt